README.md
setup.cfg
setup.py
modelfront/__init__.py
modelfront.egg-info/PKG-INFO
modelfront.egg-info/SOURCES.txt
modelfront.egg-info/dependency_links.txt
modelfront.egg-info/top_level.txt