Metadata-Version: 1.1
Name: modelfront
Version: 0.1
Summary: Translation quality prediction
Home-page: https://github.com/modelfront/py
Author: ModelFront
Author-email: py@modelfront.com
License: MIT
Download-URL: https://github.com/modelfront/py/archive/0.1.tar.gz
Keywords: natural language processing,text,translation,translation quality
Platform: UNKNOWN
Classifier: Development Status :: 3 - Alpha
Classifier: Intended Audience :: Developers
Classifier: License :: OSI Approved :: MIT License
Classifier: Programming Language :: Python :: 3.3
Classifier: Programming Language :: Python :: 3.4
Classifier: Programming Language :: Python :: 3.5
